[{"providerid":"HHHVC","providername":"JfzFratEkP","providergroupid":"YC0o2","providergroup":"fwtfBN","providerphone":"1520596054","level1status":"Confirmed","categoryofclosedcharts":"<5","chartsopen":9},{"providerid":"RPaBw","providername":"pHBUwCLQhI","providergroupid":"KAP55","providergroup":"BrhzKw","providerphone":"1335909734","level1status":"In Progress","categoryofclosedcharts":"<10","chartsopen":9},{"providerid":"bMU8K","providername":"BfSGKVFJGW","providergroupid":"YUTOa","providergroup":"gbfoKD","providerphone":"4803745709","level1status":"In Progress","categoryofclosedcharts":"0","chartsopen":7},{"providerid":"mBXrK","providername":"gEuGIJnmBy","providergroupid":"jSnaa","providergroup":"uzOClb","providerphone":"9839684784","level1status":"In Progress","categoryofclosedcharts":"0","chartsopen":5},{"providerid":"w1GBE","providername":"rCJllxlZmp","providergroupid":"vhts3","providergroup":"VitRYS","providerphone":"0151823049","level1status":"Confirmed","categoryofclosedcharts":"<10","chartsopen":1},{"providerid":"RCEeO","providername":"GAnavhZYDk","providergroupid":"pFFTU","providergroup":"JDFbfK","providerphone":"6915617237","level1status":"In Progress","categoryofclosedcharts":"<5","chartsopen":9},{"providerid":"IK1Bv","providername":"bGUfQqISjn","providergroupid":"lnwZD","providergroup":"igpdvQ","providerphone":"8207012914","level1status":"Waiting","categoryofclosedcharts":"<5","chartsopen":5},{"providerid":"qzYG4","providername":"USksxPPsxF","providergroupid":"C1EqW","providergroup":"BGQmgI","providerphone":"5031583026","level1status":"In Progress","categoryofclosedcharts":"0","chartsopen":6},{"providerid":"UzMp3","providername":"uVRcwzWcfM","providergroupid":"jsLou","providergroup":"IKMguG","providerphone":"2199781802","level1status":"In Progress","categoryofclosedcharts":"<10","chartsopen":2},{"providerid":"y6mqT","providername":"lSGeHXhYst","providergroupid":"BsaSK","providergroup":"wMLsCy","providerphone":"2196940688","level1status":"In Progress","categoryofclosedcharts":"<10","chartsopen":6},{"providerid":"VeLbL","providername":"SYukPCBwlf","providergroupid":"ZYW8h","providergroup":"HjCRoH","providerphone":"9404282088","level1status":"Confirmed","categoryofclosedcharts":"<5","chartsopen":2},{"providerid":"tjL0o","providername":"uGFcpANalf","providergroupid":"e02M9","providergroup":"fVQWYi","providerphone":"0954591397","level1status":"Confirmed","categoryofclosedcharts":"0","chartsopen":1},{"providerid":"efBPw","providername":"fNUSdaXrGm","providergroupid":"aqn7J","providergroup":"RcJTEv","providerphone":"6525255968","level1status":"In Progress","categoryofclosedcharts":"<5","chartsopen":3},{"providerid":"L4nHH","providername":"AHZybUTTYI","providergroupid":"04SCI","providergroup":"KtiNso","providerphone":"4507561859","level1status":"Waiting","categoryofclosedcharts":"0","chartsopen":5},{"providerid":"ZW0aa","providername":"bCVEwdkpKQ","providergroupid":"ZUCHs","providergroup":"Uppgfb","providerphone":"3213100468","level1status":"Waiting","categoryofclosedcharts":"<10","chartsopen":4},{"providerid":"Tsjpc","providername":"iEYEztKqqc","providergroupid":"vGZ5A","providergroup":"AxaZRk","providerphone":"4163813528","level1status":"In Progress","categoryofclosedcharts":"0","chartsopen":9},{"providerid":"K0UFC","providername":"njgWSfgXZM","providergroupid":"f8QVa","providergroup":"XUlClP","providerphone":"2987241786","level1status":"Confirmed","categoryofclosedcharts":"0","chartsopen":1},{"providerid":"ofEMD","providername":"pDPswGJbFP","providergroupid":"pjwgq","providergroup":"aoQSwx","providerphone":"2542927935","level1status":"Waiting","categoryofclosedcharts":"<5","chartsopen":0},{"providerid":"X0b66","providername":"XROuHMuWoq","providergroupid":"1Mba8","providergroup":"xijwFW","providerphone":"0007986827","level1status":"In Progress","categoryofclosedcharts":"0","chartsopen":8},{"providerid":"As7CE","providername":"wZIgEVFtQM","providergroupid":"mwrFq","providergroup":"NJJXoo","providerphone":"1875430854","level1status":"Confirmed","categoryofclosedcharts":"<10","chartsopen":9},{"providerid":"Fzeut","providername":"RhZKdxUuaP","providergroupid":"2oFlC","providergroup":"IPpgjm","providerphone":"6231786625","level1status":"Confirmed","categoryofclosedcharts":"<10","chartsopen":5},{"providerid":"8x4GV","providername":"OTTtUEngGz","providergroupid":"CQzAe","providergroup":"THBZSN","providerphone":"5203847413","level1status":"Confirmed","categoryofclosedcharts":"<5","chartsopen":9},{"providerid":"gWCcA","providername":"xvGyfdjXxD","providergroupid":"1MttW","providergroup":"GBswsO","providerphone":"2110898117","level1status":"In Progress","categoryofclosedcharts":"<10","chartsopen":9},{"providerid":"ZL7eJ","providername":"AUVcCzlJTU","providergroupid":"Fwfsm","providergroup":"USHyYZ","providerphone":"4755024990","level1status":"Confirmed","categoryofclosedcharts":"0","chartsopen":8},{"providerid":"iGyt1","providername":"IxvETjttHA","providergroupid":"9H9ok","providergroup":"MJZAeL","providerphone":"6986601842","level1status":"Confirmed","categoryofclosedcharts":"0","chartsopen":8},{"providerid":"Cqx8D","providername":"UnhqwFnLNN","providergroupid":"AqiDO","providergroup":"MihjlS","providerphone":"9981811453","level1status":"Confirmed","categoryofclosedcharts":"<5","chartsopen":4},{"providerid":"ybjcX","providername":"yaTFoWAgZC","providergroupid":"sGPG0","providergroup":"xGOizd","providerphone":"7764823982","level1status":"In Progress","categoryofclosedcharts":"<10","chartsopen":0},{"providerid":"E3e78","providername":"xXtlGqjmzo","providergroupid":"zHWAA","providergroup":"eSqFKc","providerphone":"5183103168","level1status":"In Progress","categoryofclosedcharts":"<10","chartsopen":5},{"providerid":"WYtmQ","providername":"EjKEIiyVMz","providergroupid":"r0DwX","providergroup":"WfJDSP","providerphone":"1611917910","level1status":"In Progress","categoryofclosedcharts":"<5","chartsopen":3},{"providerid":"QkgXp","providername":"VQeLBOmJpL","providergroupid":"4KLGE","providergroup":"yfWKqF","providerphone":"7768326309","level1status":"Waiting","categoryofclosedcharts":"<10","chartsopen":2},{"providerid":"0ThaH","providername":"TBSUctjvJq","providergroupid":"Qkdo2","providergroup":"WLrAVT","providerphone":"3711874506","level1status":"Confirmed","categoryofclosedcharts":"0","chartsopen":3},{"providerid":"CqQjb","providername":"yNURnLYJVa","providergroupid":"H8t85","providergroup":"nglwTX","providerphone":"8141002589","level1status":"Confirmed","categoryofclosedcharts":"<5","chartsopen":4},{"providerid":"Ykmj3","providername":"bvrnvvFOtB","providergroupid":"fgXOI","providergroup":"guWBWc","providerphone":"2556691726","level1status":"Waiting","categoryofclosedcharts":"0","chartsopen":2},{"providerid":"JWIa0","providername":"PbDOwLweRj","providergroupid":"E7w18","providergroup":"FkEgFa","providerphone":"7989755622","level1status":"In Progress","categoryofclosedcharts":"<10","chartsopen":2},{"providerid":"YnyOi","providername":"sWGYTXMHms","providergroupid":"8jYFd","providergroup":"NtvReL","providerphone":"5591956491","level1status":"Confirmed","categoryofclosedcharts":"<10","chartsopen":6},{"providerid":"QNIvq","providername":"uBSLEKwIsc","providergroupid":"rXzqA","providergroup":"fThwMt","providerphone":"1169210945","level1status":"In Progress","categoryofclosedcharts":"<10","chartsopen":3},{"providerid":"IZIcR","providername":"WWRIyWsNrB","providergroupid":"JvIzU","providergroup":"rCouoX","providerphone":"7365195447","level1status":"Confirmed","categoryofclosedcharts":"0","chartsopen":7},{"providerid":"6QUHl","providername":"vzXBaztVqs","providergroupid":"nmx89","providergroup":"nwVfNA","providerphone":"2671401005","level1status":"In Progress","categoryofclosedcharts":"<10","chartsopen":5},{"providerid":"4X9ba","providername":"VEGEQBFFLE","providergroupid":"kLaRz","providergroup":"MPgZuQ","providerphone":"1464984752","level1status":"In Progress","categoryofclosedcharts":"<10","chartsopen":4},{"providerid":"3ZNK4","providername":"rDePotPtvW","providergroupid":"BaBrf","providergroup":"PhjCtU","providerphone":"5432682657","level1status":"Confirmed","categoryofclosedcharts":"<10","chartsopen":6},{"providerid":"Lrrfg","providername":"upvtskzELE","providergroupid":"EmKLW","providergroup":"DJlcpS","providerphone":"8018465375","level1status":"Waiting","categoryofclosedcharts":"0","chartsopen":2},{"providerid":"Z3jFs","providername":"bCIUpNEDvr","providergroupid":"EBq5S","providergroup":"Rcpxga","providerphone":"4329335036","level1status":"Waiting","categoryofclosedcharts":"<5","chartsopen":0},{"providerid":"ElWsr","providername":"FcsTvmTBBf","providergroupid":"YKQib","providergroup":"rtGtZx","providerphone":"1391020522","level1status":"In Progress","categoryofclosedcharts":"0","chartsopen":2},{"providerid":"9K5WD","providername":"JDaLmHPWNW","providergroupid":"gF2Gl","providergroup":"NmRdqF","providerphone":"4478577419","level1status":"Waiting","categoryofclosedcharts":"<10","chartsopen":1},{"providerid":"tCklq","providername":"lSrTxiuCHf","providergroupid":"YdFMi","providergroup":"KAuEes","providerphone":"9607991769","level1status":"Confirmed","categoryofclosedcharts":"<5","chartsopen":1},{"providerid":"XE18P","providername":"FddgKWzume","providergroupid":"PBSNr","providergroup":"LHulWn","providerphone":"5571797588","level1status":"In Progress","categoryofclosedcharts":"<5","chartsopen":6},{"providerid":"xRuZ7","providername":"hhlUtpqYyi","providergroupid":"D292i","providergroup":"wojjDx","providerphone":"7071341224","level1status":"In Progress","categoryofclosedcharts":"<10","chartsopen":0},{"providerid":"eup53","providername":"ezsMntycUA","providergroupid":"U7myX","providergroup":"fazIin","providerphone":"8522554026","level1status":"In Progress","categoryofclosedcharts":"0","chartsopen":7},{"providerid":"ig2uh","providername":"UUuXTPNMgV","providergroupid":"ATw9b","providergroup":"cXrxkZ","providerphone":"6223358270","level1status":"Confirmed","categoryofclosedcharts":"<10","chartsopen":3},{"providerid":"QEcXj","providername":"yyLCptCWLL","providergroupid":"1usyU","providergroup":"rGDRHa","providerphone":"8329935207","level1status":"Confirmed","categoryofclosedcharts":"0","chartsopen":5},{"providerid":"ItwMd","providername":"MBAgvCORlJ","providergroupid":"83vJI","providergroup":"RQpcOH","providerphone":"8748237218","level1status":"Confirmed","categoryofclosedcharts":"<10","chartsopen":8},{"providerid":"LMQE3","providername":"skgQlxCcZh","providergroupid":"inhRL","providergroup":"wjvkzq","providerphone":"7401543647","level1status":"Confirmed","categoryofclosedcharts":"<10","chartsopen":2},{"providerid":"yWnHJ","providername":"UjvoMLVIqY","providergroupid":"tvQOs","providergroup":"qKBPIk","providerphone":"0614843053","level1status":"In Progress","categoryofclosedcharts":"0","chartsopen":2},{"providerid":"NgyBK","providername":"YbRBhSrjND","providergroupid":"4cTBj","providergroup":"nBYPnN","providerphone":"2687490406","level1status":"Waiting","categoryofclosedcharts":"0","chartsopen":6},{"providerid":"CGbGo","providername":"OSjTMVJdUb","providergroupid":"vh8Mb","providergroup":"LcbxoS","providerphone":"3311112337","level1status":"In Progress","categoryofclosedcharts":"<10","chartsopen":8},{"providerid":"0zkev","providername":"KpKGLuxnlU","providergroupid":"ms8Jc","providergroup":"poKEgz","providerphone":"7068015566","level1status":"Waiting","categoryofclosedcharts":"<5","chartsopen":6},{"providerid":"SQ0zt","providername":"cesTCCQiMi","providergroupid":"ls4ol","providergroup":"lgYkIk","providerphone":"9495693471","level1status":"Waiting","categoryofclosedcharts":"0","chartsopen":4},{"providerid":"Llvo8","providername":"LMEWAKaRSJ","providergroupid":"vqjfT","providergroup":"PovbpN","providerphone":"1381967820","level1status":"In Progress","categoryofclosedcharts":"0","chartsopen":5},{"providerid":"2zXKp","providername":"lDHsXilepB","providergroupid":"hS7iA","providergroup":"ioRZSv","providerphone":"6191675773","level1status":"Waiting","categoryofclosedcharts":"<10","chartsopen":1},{"providerid":"AxUCo","providername":"uohLMDGdLY","providergroupid":"LQ02w","providergroup":"cECsNg","providerphone":"6423926989","level1status":"Confirmed","categoryofclosedcharts":"<5","chartsopen":8},{"providerid":"xwo8N","providername":"JnkMYcUvMX","providergroupid":"eWqKQ","providergroup":"OfzlQG","providerphone":"9138359078","level1status":"Confirmed","categoryofclosedcharts":"0","chartsopen":4},{"providerid":"jnH5M","providername":"oNHRNWKfdv","providergroupid":"pkwIh","providergroup":"pofrsW","providerphone":"1318409032","level1status":"Confirmed","categoryofclosedcharts":"0","chartsopen":9},{"providerid":"O5C76","providername":"yoOYHAlnPt","providergroupid":"JSWgD","providergroup":"cTgjPT","providerphone":"1365634410","level1status":"In Progress","categoryofclosedcharts":"<5","chartsopen":8},{"providerid":"uTFaA","providername":"xnPPzSuzRK","providergroupid":"uuJYM","providergroup":"grHrKp","providerphone":"0407320286","level1status":"In Progress","categoryofclosedcharts":"0","chartsopen":1},{"providerid":"tXTIH","providername":"PlIofdkanM","providergroupid":"7nUa9","providergroup":"evhuLf","providerphone":"5815479044","level1status":"Waiting","categoryofclosedcharts":"<10","chartsopen":7},{"providerid":"wRMJ3","providername":"XQtByutVgc","providergroupid":"tTrYH","providergroup":"eZwabJ","providerphone":"5135928825","level1status":"Waiting","categoryofclosedcharts":"<5","chartsopen":3},{"providerid":"NZz3D","providername":"mNnpBlejrh","providergroupid":"vDQ2y","providergroup":"aQJRTP","providerphone":"6108740948","level1status":"Waiting","categoryofclosedcharts":"0","chartsopen":0},{"providerid":"pOpJf","providername":"upGjLRxhvo","providergroupid":"UkNWq","providergroup":"MVhCsK","providerphone":"4102779887","level1status":"Confirmed","categoryofclosedcharts":"<5","chartsopen":9},{"providerid":"Wj8AP","providername":"rRshBNzylM","providergroupid":"oBxIz","providergroup":"mlPVUp","providerphone":"8758118827","level1status":"Waiting","categoryofclosedcharts":"<5","chartsopen":4},{"providerid":"69DQa","providername":"EVcKOPsang","providergroupid":"ekuJm","providergroup":"brsORs","providerphone":"0622313372","level1status":"In Progress","categoryofclosedcharts":"<5","chartsopen":2},{"providerid":"i6wNS","providername":"KHEGQSYtRE","providergroupid":"oBYDy","providergroup":"ElvDaO","providerphone":"0304194672","level1status":"Confirmed","categoryofclosedcharts":"<5","chartsopen":6},{"providerid":"kras6","providername":"lWBKHRtcuT","providergroupid":"JmW4q","providergroup":"jnzJJA","providerphone":"5010878630","level1status":"Waiting","categoryofclosedcharts":"0","chartsopen":3},{"providerid":"9OWTo","providername":"jYTEdAjDXu","providergroupid":"SxnEO","providergroup":"FzQKLK","providerphone":"3038391450","level1status":"Waiting","categoryofclosedcharts":"<10","chartsopen":6},{"providerid":"QgkWa","providername":"nodgDTmMQr","providergroupid":"Te27n","providergroup":"RIECgP","providerphone":"5944818630","level1status":"Confirmed","categoryofclosedcharts":"<5","chartsopen":4},{"providerid":"f97yV","providername":"oXPNHaWHZr","providergroupid":"BjTMQ","providergroup":"hBdrsC","providerphone":"5230328234","level1status":"In Progress","categoryofclosedcharts":"<10","chartsopen":3},{"providerid":"Ve6TX","providername":"QcuIruCsXC","providergroupid":"Rf4Bl","providergroup":"WNDgmM","providerphone":"7472092848","level1status":"Confirmed","categoryofclosedcharts":"<5","chartsopen":4},{"providerid":"4hQhI","providername":"ZwdoAfNEjt","providergroupid":"ZzZYW","providergroup":"NOEASF","providerphone":"3836520538","level1status":"In Progress","categoryofclosedcharts":"<5","chartsopen":2},{"providerid":"l8puh","providername":"pxsCRpsmZs","providergroupid":"CKJue","providergroup":"elDtkt","providerphone":"3048661080","level1status":"Confirmed","categoryofclosedcharts":"0","chartsopen":7},{"providerid":"p5IHx","providername":"zKgvsILiOC","providergroupid":"xC2uV","providergroup":"maASld","providerphone":"1812622850","level1status":"Waiting","categoryofclosedcharts":"0","chartsopen":9},{"providerid":"u6yH5","providername":"HxXJKoazxa","providergroupid":"7u6lp","providergroup":"QLLiEv","providerphone":"9153027413","level1status":"Waiting","categoryofclosedcharts":"<5","chartsopen":3},{"providerid":"j3KVc","providername":"ZFlUagpgCV","providergroupid":"E8zc0","providergroup":"WLrTIo","providerphone":"6456109946","level1status":"Confirmed","categoryofclosedcharts":"<10","chartsopen":7},{"providerid":"29sew","providername":"qFqCdfOSQW","providergroupid":"WEjb1","providergroup":"cDXWcl","providerphone":"5364642950","level1status":"Confirmed","categoryofclosedcharts":"0","chartsopen":1},{"providerid":"mNyqu","providername":"IyuNGVqFcq","providergroupid":"C94bw","providergroup":"GRqHJe","providerphone":"9845098493","level1status":"Confirmed","categoryofclosedcharts":"<5","chartsopen":3},{"providerid":"ypR4u","providername":"LTWEHpBRWl","providergroupid":"Qu1dP","providergroup":"MnZdSw","providerphone":"1932458836","level1status":"In Progress","categoryofclosedcharts":"<5","chartsopen":4},{"providerid":"E5tyH","providername":"JhRmSAQKPm","providergroupid":"4XxwY","providergroup":"conAQl","providerphone":"1833073110","level1status":"In Progress","categoryofclosedcharts":"<5","chartsopen":6},{"providerid":"bTWEX","providername":"EfGdgDEicw","providergroupid":"79TZC","providergroup":"JJbaxN","providerphone":"9011156119","level1status":"In Progress","categoryofclosedcharts":"<10","chartsopen":2},{"providerid":"lo5d1","providername":"zwKbOMlsVT","providergroupid":"9zUdE","providergroup":"nmHSTQ","providerphone":"2131365343","level1status":"In Progress","categoryofclosedcharts":"<10","chartsopen":8},{"providerid":"J84xZ","providername":"HsrVkFjMFw","providergroupid":"qkvwU","providergroup":"wDiktb","providerphone":"1629629090","level1status":"In Progress","categoryofclosedcharts":"<10","chartsopen":1},{"providerid":"EHPiP","providername":"dYMEQmYKGf","providergroupid":"zXih5","providergroup":"mGxmpl","providerphone":"4101072351","level1status":"Confirmed","categoryofclosedcharts":"<10","chartsopen":0},{"providerid":"AZghC","providername":"VfMESROYaO","providergroupid":"RlTMC","providergroup":"cZBEKX","providerphone":"6022336525","level1status":"Waiting","categoryofclosedcharts":"<5","chartsopen":2},{"providerid":"wplN4","providername":"VpxackUJDb","providergroupid":"CUd9W","providergroup":"ChqCtd","providerphone":"5086062552","level1status":"Waiting","categoryofclosedcharts":"0","chartsopen":2},{"providerid":"wrV1L","providername":"dvjiDaYwFa","providergroupid":"yRMH5","providergroup":"yfcGWm","providerphone":"0174206294","level1status":"Confirmed","categoryofclosedcharts":"<10","chartsopen":1},{"providerid":"d8dcC","providername":"oHawLHlPfc","providergroupid":"lK6f0","providergroup":"YifFnW","providerphone":"5426264427","level1status":"In Progress","categoryofclosedcharts":"<5","chartsopen":6},{"providerid":"4JCQw","providername":"XNRblOKpyk","providergroupid":"7k0wx","providergroup":"wWLgHa","providerphone":"1931609790","level1status":"Waiting","categoryofclosedcharts":"0","chartsopen":3},{"providerid":"8ZgH4","providername":"pQTmzAmcBs","providergroupid":"l2Lba","providergroup":"blXFhB","providerphone":"5605428556","level1status":"Confirmed","categoryofclosedcharts":"0","chartsopen":2},{"providerid":"jRjOf","providername":"MdSgmeHswr","providergroupid":"4BNQl","providergroup":"NhUaEi","providerphone":"2964497843","level1status":"Waiting","categoryofclosedcharts":"0","chartsopen":6},{"providerid":"TGOB9","providername":"MUshwJJJQe","providergroupid":"Z0HMW","providergroup":"neokbX","providerphone":"4579926965","level1status":"Confirmed","categoryofclosedcharts":"<10","chartsopen":4},{"providerid":"SlXzW","providername":"kDIdpYDEcl","providergroupid":"8c7Ua","providergroup":"ZQunqL","providerphone":"9272144514","level1status":"Waiting","categoryofclosedcharts":"0","chartsopen":8},{"providerid":"Qb1dn","providername":"SiSKGRJATt","providergroupid":"Z3VHy","providergroup":"tzyPyw","providerphone":"1989814322","level1status":"Waiting","categoryofclosedcharts":"<10","chartsopen":9},{"providerid":"rUG7J","providername":"EVjuStEUQR","providergroupid":"k30VE","providergroup":"FVqlvy","providerphone":"8549485598","level1status":"Waiting","categoryofclosedcharts":"<10","chartsopen":8}]